setup.cfg
setup.py
django_rest_framework_oauth.egg-info/PKG-INFO
django_rest_framework_oauth.egg-info/SOURCES.txt
django_rest_framework_oauth.egg-info/dependency_links.txt
django_rest_framework_oauth.egg-info/requires.txt
django_rest_framework_oauth.egg-info/top_level.txt
rest_framework_oauth/__init__.py
rest_framework_oauth/authentication.py
rest_framework_oauth/permissions.py