Metadata-Version: 1.1
Name: django-rest-framework-oauth
Version: 0.0.2
Summary: OAuth Support for Django REST Framework
Home-page: https://github.com/jlafon/django-rest-framework-oauth
Author: Jharrod LaFon
Author-email: jlafon@eyesopen.com
License: BSD
Platform: UNKNOWN
Classifier: Development Status :: 4 - Beta
Classifier: Environment :: Web Environment
Classifier: Framework :: Django
Classifier: Intended Audience :: Developers
Classifier: License :: OSI Approved :: BSD License
Classifier: Operating System :: OS Independent
Classifier: Programming Language :: Python
Classifier: Programming Language :: Python :: 3
Classifier: Topic :: Internet :: WWW/HTTP
